synthetic/__init__.py
synthetic/eval/__init__.py
synthetic/eval/__main__.py
synthetic/eval/cli.py
synthetic/eval/graph.py
synthetic/eval/score.py
synthetic/loader.py
synthetic/product.dat
synthetic/py.typed
synthetic/review.dat
synthetic/reviewer.dat
rgmining_synthetic_dataset-0.9.5.dist-info/METADATA
rgmining_synthetic_dataset-0.9.5.dist-info/WHEEL
rgmining_synthetic_dataset-0.9.5.dist-info/entry_points.txt
rgmining_synthetic_dataset-0.9.5.dist-info/licenses/COPYING
rgmining_synthetic_dataset-0.9.5.dist-info/RECORD
