Metadata-Version: 2.4
Name: rgmining-synthetic-dataset
Version: 0.9.5
Summary: A synthetic dataset for Review graph mining project
License-Expression: GPL-3.0-only
License-File: COPYING
Keywords: dataset,dexa,graph,mining,review
Author: Junpei Kawamoto
Author-email: kawamoto.junpei@gmail.com
Requires-Python: >=3.11
Classifier: Development Status :: 4 - Beta
Classifier: Intended Audience :: Science/Research
Classifier: License :: OSI Approved :: GNU General Public License v3 (GPLv3)
Classifier: Natural Language :: English
Classifier: Programming Language :: Python
Classifier: Programming Language :: Python :: 3 :: Only
Classifier: Programming Language :: Python :: 3.11
Classifier: Programming Language :: Python :: 3.12
Classifier: Programming Language :: Python :: 3.13
Classifier: Programming Language :: Python :: 3.14
Classifier: Topic :: Scientific/Engineering :: Information Analysis
Classifier: Topic :: Software Development :: Libraries
Requires-Dist: click (>=8.1)
Requires-Dist: matplotlib (>=3.10)
Requires-Dist: numpy (>=2.2)
Project-URL: Documentation, https://rgmining.github.io/synthetic/
Project-URL: Homepage, https://rgmining.github.io/synthetic/
Project-URL: Repository, https://github.com/rgmining/synthetic
